codeindexer/__init__.py
codeindexer/cli.py
codeindexer/gitignore_parser.py
codeindexer/indexer.py
codeindexer/utils.py
codeindexer/tests/test_indexer.py
codeindexer-0.1.2.dist-info/licenses/LICENSE
codeindexer-0.1.2.dist-info/METADATA
codeindexer-0.1.2.dist-info/WHEEL
codeindexer-0.1.2.dist-info/entry_points.txt
codeindexer-0.1.2.dist-info/top_level.txt
codeindexer-0.1.2.dist-info/RECORD
