Metadata-Version: 2.4
Name: codeindexer
Version: 0.1.2
Summary: A lightweight CLI to index a codebase and create a context-ready prompt file for LLM.
Author-email: Franklin Kemta <hi@franklinkemta.com>
Project-URL: Homepage, https://github.com/franklinkemta/codeindexer
Project-URL: Bug Tracker, https://github.com/franklinkemta/codeindexer/issues
Keywords: productivity,open-source,code,prompt,indexing,gemini,codebase,llama,cursor,copilot,copy-paste,claude,groq,llm,prompt-engineering,llms,chatgpt,deepseek
Classifier: Programming Language :: Python :: 3
Classifier: License :: OSI Approved :: MIT License
Classifier: Operating System :: OS Independent
Requires-Python: >=3.7
License-File: LICENSE
Requires-Dist: click>=8.0.0
Requires-Dist: rich>=10.0.0
Provides-Extra: dev
Requires-Dist: pytest>=7.0.0; extra == "dev"
Requires-Dist: black>=22.0.0; extra == "dev"
Requires-Dist: flake8>=5.0.0; extra == "dev"
Requires-Dist: mypy>=0.9.0; extra == "dev"
Requires-Dist: isort>=5.0.0; extra == "dev"
Requires-Dist: pytest-cov>=3.0.0; extra == "dev"
Requires-Dist: twine>=4.0.0; extra == "dev"
Requires-Dist: build>=0.8.0; extra == "dev"
Dynamic: license-file
